cynthia/__init__.py
cynthia/__main__.py
cynthia/tools/__init__.py
cynthia/tools/nodes.py
cynthia/tools/parser.py
cynthia/tools/shell.py
cynthia/tools/interpreter/__init__.py
cynthia/tools/interpreter/exceptions.py
cynthia/tools/interpreter/interpreter.py
cynthia/tools/lexer/__init__.py
cynthia/tools/lexer/lexer.py
cynthia/tools/lexer/lexer_utils.py
cynthia/tools/lexer/logics.py
cynthia/tools/lexer/supported_tokens.py
cynthia/tools/lexer/tokens.py
cynthia_language-0.1.3.dist-info/METADATA
cynthia_language-0.1.3.dist-info/WHEEL
cynthia_language-0.1.3.dist-info/licenses/LICENSE
cynthia_language-0.1.3.dist-info/RECORD
