Metadata-Version: 2.1
Name: cynthia-language
Version: 0.1.3
Summary: Cynthia is a small interpreted script language for basic mathematical expressions.
Project-URL: Homepage, https://github.com/krisztianszenasi/cynthia
Project-URL: Bug Tracker, https://github.com/krisztianszenasi/cynthia/issues
Author-email: Krisztian Szenasi <szenasi999@gmail.com>
License-File: LICENSE
Classifier: License :: OSI Approved :: MIT License
Classifier: Operating System :: OS Independent
Classifier: Programming Language :: Python :: 3
Requires-Python: >=3.11
